b2c_oauth_client/__init__.py
b2c_oauth_client/client.py
b2c_oauth_client/exceptions.py
b2c_oauth_client/models.py
b2c_oauth_client/py.typed
b2c_oauth_client-0.0.4.dist-info/METADATA
b2c_oauth_client-0.0.4.dist-info/WHEEL
b2c_oauth_client-0.0.4.dist-info/licenses/LICENSE
b2c_oauth_client-0.0.4.dist-info/RECORD
