Metadata-Version: 2.4
Name: b2c-oauth-client
Version: 0.0.4
Summary: Simple Python library for Azure B2C OAuth2 refresh token authentication
Project-URL: Homepage, https://github.com/jvuori/b2c-oauth-client
Project-URL: Documentation, https://github.com/jvuori/b2c-oauth-client#readme
Project-URL: Repository, https://github.com/jvuori/b2c-oauth-client.git
Project-URL: Issues, https://github.com/jvuori/b2c-oauth-client/issues
Author-email: Jaakko Vuori <jaakko.vuori@gmail.com>
License: MIT
License-File: LICENSE
Keywords: authentication,azure,b2c,oauth2,refresh-token
Classifier: Development Status :: 4 - Beta
Classifier: Intended Audience :: Developers
Classifier: License :: OSI Approved :: MIT License
Classifier: Programming Language :: Python :: 3
Classifier: Programming Language :: Python :: 3.10
Classifier: Programming Language :: Python :: 3.11
Classifier: Programming Language :: Python :: 3.12
Classifier: Programming Language :: Python :: 3.13
Classifier: Topic :: Internet :: WWW/HTTP
Classifier: Topic :: Software Development :: Libraries :: Python Modules
Requires-Python: >=3.10
Requires-Dist: requests>=2.31.0
Provides-Extra: dev
Requires-Dist: mypy>=1.5.0; extra == 'dev'
Requires-Dist: pytest-cov>=4.0.0; extra == 'dev'
Requires-Dist: pytest>=7.0.0; extra == 'dev'
Requires-Dist: ruff>=0.1.0; extra == 'dev'
Requires-Dist: types-requests>=2.31.0; extra == 'dev'
